pystrsim-0.1.0.dist-info/METADATA
pystrsim-0.1.0.dist-info/WHEEL
pystrsim-0.1.0.dist-info/license_files/LICENSE
pystrsim/__init__.py
pystrsim/pystrsim.cpython-38-darwin.so
pystrsim-0.1.0.dist-info/RECORD
